{
  "type": "draconicevolution:fusion_crafting",
  "catalyst": {
    "item": "minecraft:nether_star"
  },
  "ingredients": [
    {"item": "draconicevolution:chaotic_core"},
    {"item": "draconicevolution:chaotic_core"},
    {"item": "draconicevolution:chaotic_energy_core"},
    {"item": "draconicevolution:chaotic_energy_core"},
    {"item": "draconicevolution:large_chaos_frag"},
    {"item": "draconicevolution:large_chaos_frag"},
    {"item": "draconicevolution:item_chaotic_damage"},
    {"item": "draconicevolution:item_chaotic_damage"},
    {"item": "minecraft:tnt"},
    {"item": "minecraft:end_crystal"},
    {"item": "draconicevolution:draconic_energy_core"},
    {"item": "draconicevolution:draconic_energy_core"}
  ],
  "result": {
    "item": "dgmodules:cataclysm_arrow_module",
    "count": 1
  },
  "tier": "CHAOTIC",
  "total_energy": 8000000000
}
