{
  "type": "draconicevolution:fusion_crafting",
  "catalyst": {
    "item": "draconicevolution:item_draconic_damage"
  },
  "ingredients": [
    {
      "consume": true,
      "ingredient": {
        "item": "draconicevolution:awakened_core"
      }
    },
    {
      "consume": true,
      "ingredient": {
        "item": "draconicevolution:awakened_core"
      }
    },
    {
      "consume": true,
      "ingredient": {
        "item": "draconicevolution:draconic_energy_core"
      }
    },
    {
      "consume": true,
      "ingredient": {
        "item": "draconicevolution:draconic_energy_core"
      }
    },
    {
      "consume": true,
      "ingredient": {
        "item": "draconicevolution:draconium_core"
      }
    },
    {
      "consume": true,
      "ingredient": {
        "item": "draconicevolution:draconium_core"
      }
    },
    {
      "consume": true,
      "ingredient": {
        "item": "dgmodules:draconic_hp_damage_module"
      }
    },
    {
      "consume": true,
      "ingredient": {
        "item": "minecraft:nether_star"
      }
    }
  ],
  "result": {
    "id": "dgmodules:frame_breaker_module",
    "count": 1
  },
  "techLevel": "draconic",
  "totalEnergy": 96000000
}
